{"question_type": "DESCRIPTION", "fact_or_opinion": "OPINION", "id": 18403, "question": "\u9a81\u9f99653\u548c626\u54ea\u4e2a\u597d", "part": "zhidao_train"}
{"question_type": "ENTITY", "fact_or_opinion": "OPINION", "id": 53773, "question": "\u897f\u5b89\u7a7a\u8c03\u79fb\u673a\u591a\u5c11\u94b1", "part": "zhidao_train"}
{"question_type": "YES_NO", "fact_or_opinion": "OPINION", "id": 18892, "question": "\u8ba8\u9b3c\u4f202\u597d\u73a9\u5417", "part": "zhidao_train"}
{"question_type": "DESCRIPTION", "fact_or_opinion": "FACT", "id": 75236, "question": "\u51a0\u72b6\u6c9f\u767d\u8272\u5206\u6ccc\u7269", "part": "zhidao_train"}
{"question_type": "DESCRIPTION", "fact_or_opinion": "FACT", "id": 15460, "question": "ar\u548cvr\u7684\u533a\u522b", "part": "zhidao_train"}
{"question_type": "YES_NO", "fact_or_opinion": "OPINION", "id": 69751, "question": "\u6258\u5e15\u77f3\u6709\u6536\u85cf\u4ef7\u503c\u5417", "part": "zhidao_train"}
{"question_type": "YES_NO", "fact_or_opinion": "OPINION", "id": 45831, "question": "\u5e9e\u8d1d\u672b\u65e5\u662f\u771f\u5b9e\u7684\u5417", "part": "zhidao_train"}
{"question_type": "DESCRIPTION", "fact_or_opinion": "OPINION", "id": 11128, "question": "\u811a\u62bd\u7b4b", "part": "zhidao_train"}
{"question_type": "DESCRIPTION", "fact_or_opinion": "FACT", "id": 44836, "question": "\u4fa0\u76d7\u730e\u8f66\u624b\u5723\u5b89\u5730\u5217\u65af\u624b\u673a\u7248\u600e\u4e48\u8f93\u79d8\u7c4d", "part": "zhidao_train"}
{"question_type": "ENTITY", "fact_or_opinion": "OPINION", "id": 3422, "question": "\u4e00\u4ea9\u5927\u68da\u517b\u9e45\u591a\u5c11\u53ea", "part": "zhidao_train"}
{"question_type": "DESCRIPTION", "fact_or_opinion": "FACT", "id": 7270, "question": "\u53ef\u63a7\u7845\u8c03\u5149\u539f\u7406", "part": "zhidao_train"}
{"question_type": "DESCRIPTION", "fact_or_opinion": "FACT", "id": 15567, "question": "bios\u7535\u6c60\u6ca1\u7535\u4e86\u4f1a\u600e\u4e48\u6837", "part": "zhidao_train"}
{"question_type": "ENTITY", "fact_or_opinion": "FACT", "id": 41831, "question": "\u4e00\u52a03t\u53ef\u4ee5\u5237\u4ec0\u4e48\u7cfb\u7edf", "part": "zhidao_train"}
{"question_type": "DESCRIPTION", "fact_or_opinion": "FACT", "id": 31622, "question": "\u5fae\u4fe1\u670b\u53cb\u5708\u600e\u4e48\u53d1\u957f\u89c6\u9891", "part": "zhidao_train"}
{"question_type": "ENTITY", "fact_or_opinion": "OPINION", "id": 53887, "question": "\u63d0\u83ab\u54ea\u4e2a\u76ae\u80a4\u597d", "part": "zhidao_train"}
{"question_type": "DESCRIPTION", "fact_or_opinion": "FACT", "id": 69609, "question": "\u725b\u987f\u671b\u8fdc\u955c\u6210\u50cf\u539f\u7406", "part": "zhidao_train"}
{"question_type": "DESCRIPTION", "fact_or_opinion": "OPINION", "id": 20044, "question": "\u6c34\u51b7\u548c\u98ce\u51b7\u54ea\u4e2a\u597d", "part": "zhidao_train"}
{"question_type": "DESCRIPTION", "fact_or_opinion": "FACT", "id": 2616, "question": "\u9965\u8352\u5de8\u9e7f\u600e\u4e48\u6253", "part": "zhidao_train"}
{"question_type": "DESCRIPTION", "fact_or_opinion": "FACT", "id": 56739, "question": "excel\u8f93\u5165\u6570\u5b57\u53d8\u6210\u65e5\u671f", "part": "zhidao_train"}
{"question_type": "DESCRIPTION", "fact_or_opinion": "FACT", "id": 27404, "question": "ppt\u5e95\u677f\u5982\u4f55\u4fee\u6539", "part": "zhidao_train"}
{"question_type": "ENTITY", "fact_or_opinion": "FACT", "id": 43796, "question": "\u9f99\u95e8\u9556\u5c403\u4ec0\u4e48\u65f6\u5019\u51fa", "part": "zhidao_train"}
{"question_type": "ENTITY", "fact_or_opinion": "FACT", "id": 39066, "question": "\u6b66\u6c49\u516c\u79ef\u91d1\u8d37\u6b3e\u989d\u5ea6", "part": "zhidao_train"}
{"question_type": "DESCRIPTION", "fact_or_opinion": "FACT", "id": 25541, "question": "cad\u4e2d\u95f4\u6ed1\u8f6e\u4e0d\u80fd\u5e73\u79fb", "part": "zhidao_train"}
{"question_type": "DESCRIPTION", "fact_or_opinion": "OPINION", "id": 38042, "question": "\u4e09\u6587\u9c7c\u76ae\u600e\u4e48\u5403", "part": "zhidao_train"}
{"question_type": "ENTITY", "fact_or_opinion": "OPINION", "id": 87065, "question": "\u6c34\u8349\u6db2\u80a5\u4ec0\u4e48\u724c\u5b50\u597d", "part": "zhidao_train"}
{"question_type": "ENTITY", "fact_or_opinion": "FACT", "id": 75414, "question": "1\u82f1\u5bf8\u7b49\u4e8e\u591a\u5c11mm", "part": "zhidao_train"}
{"question_type": "DESCRIPTION", "fact_or_opinion": "FACT", "id": 31637, "question": "a107860k\u96c6\u663e\u76f8\u5f53\u4e8e", "part": "zhidao_train"}
{"question_type": "DESCRIPTION", "fact_or_opinion": "FACT", "id": 71095, "question": "\u516c\u76ca\u5e7c\u513f\u56ed\u548c\u516c\u7acb\u5e7c\u513f\u56ed\u7684\u533a\u522b", "part": "zhidao_train"}
{"question_type": "DESCRIPTION", "fact_or_opinion": "FACT", "id": 33320, "question": "win10\u8ba1\u7b97\u5668\u6253\u4e0d\u5f00", "part": "zhidao_train"}
{"question_type": "ENTITY", "fact_or_opinion": "OPINION", "id": 14217, "question": "\u6597\u9c7c\u4eba\u6c145\u4e07\u6709\u591a\u5c11\u6536\u5165", "part": "zhidao_train"}
{"question_type": "DESCRIPTION", "fact_or_opinion": "FACT", "id": 38068, "question": "\u602a\u7269\u730e\u4ebap3\u5173\u952e\u4efb\u52a1", "part": "zhidao_train"}
{"question_type": "DESCRIPTION", "fact_or_opinion": "FACT", "id": 86878, "question": "\u5251\u7f51\u4e09\u600e\u4e48\u8d5a\u94b1\u5feb", "part": "zhidao_train"}
{"question_type": "ENTITY", "fact_or_opinion": "FACT", "id": 78938, "question": "\u4e52\u4e53\u7403\u684c\u6807\u51c6\u5c3a\u5bf8", "part": "zhidao_train"}
{"question_type": "DESCRIPTION", "fact_or_opinion": "OPINION", "id": 19355, "question": "\u738b\u8005\u8363\u8000\u6b66\u9053\u5927\u4f1a\u600e\u4e48\u6253", "part": "zhidao_train"}
{"question_type": "DESCRIPTION", "fact_or_opinion": "FACT", "id": 40708, "question": "\u600e\u4e48\u5f00\u901a\u5fae\u4fe1\u516c\u4f17\u53f7", "part": "zhidao_train"}
{"question_type": "DESCRIPTION", "fact_or_opinion": "FACT", "id": 54505, "question": "\u661f\u9732\u8c37\u7269\u8bed\u9752\u82b1\u9c7c\u54ea\u91cc\u9493", "part": "zhidao_train"}
{"question_type": "DESCRIPTION", "fact_or_opinion": "FACT", "id": 7983, "question": "\u6606\u4ed1\u96ea\u83ca\u7684\u529f\u6548\u4e0e\u4f5c\u7528", "part": "zhidao_train"}
{"question_type": "DESCRIPTION", "fact_or_opinion": "OPINION", "id": 63260, "question": "\u759d\u6c14\u505a\u5fae\u521b\u8fd8\u662f\u5f00\u5200\u597d", "part": "zhidao_train"}
{"question_type": "YES_NO", "fact_or_opinion": "OPINION", "id": 86222, "question": "\u97e9\u535a\u58eb\u91cd\u88c5\u7cfb\u7edf\u9760\u8c31\u5417", "part": "zhidao_train"}
{"question_type": "YES_NO", "fact_or_opinion": "FACT", "id": 36045, "question": "hotfix\u662f\u4ec0\u4e48\u80fd\u5220\u9664\u5417", "part": "zhidao_train"}
{"question_type": "DESCRIPTION", "fact_or_opinion": "OPINION", "id": 34758, "question": "\u6709\u5173\u9ec4\u5c71\u7684\u8bd7\u53e5", "part": "zhidao_train"}
{"question_type": "DESCRIPTION", "fact_or_opinion": "FACT", "id": 85615, "question": "\u83ca\u82b1\u8336\u7684\u529f\u6548\u4e0e\u4f5c\u7528", "part": "zhidao_train"}
{"question_type": "ENTITY", "fact_or_opinion": "OPINION", "id": 33478, "question": "\u521d\u5b66\u5409\u4ed6\u4e70\u4ec0\u4e48\u5409\u4ed6\u597d", "part": "zhidao_train"}
{"question_type": "DESCRIPTION", "fact_or_opinion": "FACT", "id": 4833, "question": "\u75db\u98ce\u7684\u4e34\u5e8a\u8868\u73b0", "part": "zhidao_train"}
{"question_type": "DESCRIPTION", "fact_or_opinion": "OPINION", "id": 76673, "question": "\u5403\u6c99\u62c9\u7684\u597d\u5904", "part": "zhidao_train"}
{"question_type": "DESCRIPTION", "fact_or_opinion": "FACT", "id": 41055, "question": "\u94c1\u9a91\u51b2\u950b\u79d1\u6280\u600e\u4e48\u70b9", "part": "zhidao_train"}
{"question_type": "DESCRIPTION", "fact_or_opinion": "FACT", "id": 81445, "question": "\u808b\u9aa8\u9aa8\u6298\u80f8\u8154\u79ef\u6db2", "part": "zhidao_train"}
{"question_type": "DESCRIPTION", "fact_or_opinion": "FACT", "id": 16658, "question": "\u54c8\u5f17h7\u7ea2\u6807\u548c\u84dd\u6807\u533a\u522b", "part": "zhidao_train"}
{"question_type": "DESCRIPTION", "fact_or_opinion": "OPINION", "id": 45573, "question": "\u7532\u6c9f\u708e\u5982\u4f55\u6d88\u80bf\u53bb\u8113\u6c34", "part": "zhidao_train"}
{"question_type": "ENTITY", "fact_or_opinion": "OPINION", "id": 68811, "question": "\u5357\u4eac\u5fb7\u57fa\u5e7f\u573a\u8001\u677f\u662f\u8c01", "part": "zhidao_train"}
{"question_type": "DESCRIPTION", "fact_or_opinion": "OPINION", "id": 43743, "question": "\u67e0\u6aac\u8584\u8377\u79cd\u690d\u65b9\u6cd5", "part": "zhidao_train"}
{"question_type": "DESCRIPTION", "fact_or_opinion": "FACT", "id": 12957, "question": "\u7b14\u8bb0\u672c\u7535\u8111\u4eae\u5ea6\u8c03\u8282", "part": "zhidao_train"}
{"question_type": "YES_NO", "fact_or_opinion": "FACT", "id": 39035, "question": "\u6ce8\u518c\u767e\u5ea6\u8d26\u53f7\u4e00\u5b9a\u8981\u624b\u673a\u5417", "part": "zhidao_train"}
{"question_type": "DESCRIPTION", "fact_or_opinion": "FACT", "id": 69816, "question": "\u6218\u7f51\u600e\u4e48\u6539\u540d\u5b57", "part": "zhidao_train"}
{"question_type": "DESCRIPTION", "fact_or_opinion": "FACT", "id": 24899, "question": "word\u5982\u4f55\u5168\u90e8\u63a5\u53d7\u4fee\u8ba2", "part": "zhidao_train"}
{"question_type": "DESCRIPTION", "fact_or_opinion": "FACT", "id": 12555, "question": "\u652f\u4ed8\u5b9d\u5982\u4f55\u9000\u51fa\u767b\u5f55", "part": "zhidao_train"}
{"question_type": "DESCRIPTION", "fact_or_opinion": "OPINION", "id": 45669, "question": "\u5f62\u5bb9\u590f\u5929\u7684\u6210\u8bed", "part": "zhidao_train"}
{"question_type": "DESCRIPTION", "fact_or_opinion": "FACT", "id": 47509, "question": "\u600e\u4e48\u770b\u975e\u914b\u6210\u5c31\u8fdb\u5ea6", "part": "zhidao_train"}
{"question_type": "DESCRIPTION", "fact_or_opinion": "OPINION", "id": 84656, "question": "\u9762\u762b\u7684\u62a4\u7406\u65b9\u6cd5", "part": "zhidao_train"}
{"question_type": "DESCRIPTION", "fact_or_opinion": "FACT", "id": 49600, "question": "\u600e\u4e48\u6e05\u7406\u624b\u673a\u5185\u90e8\u5b58\u50a8\u7a7a\u95f4", "part": "zhidao_train"}
{"question_type": "DESCRIPTION", "fact_or_opinion": "OPINION", "id": 8205, "question": "\u83e0\u841d\u5495\u565c\u8089\u7684\u6b63\u5b97\u505a\u6cd5", "part": "zhidao_train"}
{"question_type": "DESCRIPTION", "fact_or_opinion": "FACT", "id": 45977, "question": "\u6267\u610f\u4e0d\u80af\u7684\u610f\u601d", "part": "zhidao_train"}
{"question_type": "DESCRIPTION", "fact_or_opinion": "OPINION", "id": 60942, "question": "\u79bb\u5a5a\u5973\u4eba\u5f88\u5bb9\u6613\u4e0a\u5417", "part": "zhidao_train"}
{"question_type": "DESCRIPTION", "fact_or_opinion": "FACT", "id": 19708, "question": "\u5929\u6b63\u600e\u4e48\u8c03\u51fa\u5de6\u8fb9\u5de5\u5177\u680f", "part": "zhidao_train"}
{"question_type": "ENTITY", "fact_or_opinion": "OPINION", "id": 54905, "question": "\u54c8\u5c14\u6ee8\u770b\u767d\u765c\u98ce", "part": "zhidao_train"}
{"question_type": "DESCRIPTION", "fact_or_opinion": "FACT", "id": 58407, "question": "\u9732\u5a1c\u65e0\u9650\u5927\u62db\u600e\u4e48\u8fde", "part": "zhidao_train"}
{"question_type": "DESCRIPTION", "fact_or_opinion": "FACT", "id": 14764, "question": "\u65e9\u6cc4\u6cbb\u7597\u634c\u6cd5", "part": "zhidao_train"}
{"question_type": "DESCRIPTION", "fact_or_opinion": "FACT", "id": 24245, "question": "\u5f53\u524d\u64cd\u4f5c\u73af\u5883\u4e0d\u652f\u6301\u652f\u4ed8\u5b9d\u63a7\u4ef6", "part": "zhidao_train"}
{"question_type": "ENTITY", "fact_or_opinion": "OPINION", "id": 70491, "question": "\u8868\u793a\u989c\u8272\u7684\u8bcd\u8bed", "part": "zhidao_train"}
{"question_type": "DESCRIPTION", "fact_or_opinion": "OPINION", "id": 64504, "question": "\u5c0f\u7c73\u74f7\u7816\u8d28\u91cf\u600e\u4e48\u6837", "part": "zhidao_train"}
{"question_type": "ENTITY", "fact_or_opinion": "OPINION", "id": 12545, "question": "\u597d\u542c\u7684\u8001\u6b4c", "part": "zhidao_train"}
{"question_type": "ENTITY", "fact_or_opinion": "OPINION", "id": 33869, "question": "\u674e\u5609\u8bda\u4f20\u8bb0\u54ea\u672c\u6700\u597d", "part": "zhidao_train"}
{"question_type": "ENTITY", "fact_or_opinion": "OPINION", "id": 73259, "question": "\u5251\u7075\u73b0\u5728\u4ec0\u4e48\u804c\u4e1a\u5389\u5bb3", "part": "zhidao_train"}
{"question_type": "DESCRIPTION", "fact_or_opinion": "FACT", "id": 20260, "question": "\u89c4\u5212\u8bb8\u53ef\u8bc1\u529e\u7406\u6d41\u7a0b", "part": "zhidao_train"}
{"question_type": "DESCRIPTION", "fact_or_opinion": "FACT", "id": 84489, "question": "ipad2\u8d8a\u72f1\u540e\u600e\u4e48\u5347\u7ea7", "part": "zhidao_train"}
{"question_type": "DESCRIPTION", "fact_or_opinion": "FACT", "id": 62064, "question": "excel\u600e\u4e48\u8bfb", "part": "zhidao_train"}
{"question_type": "DESCRIPTION", "fact_or_opinion": "FACT", "id": 74802, "question": "\u6cd5\u56fd\u4e3a\u4ec0\u4e48\u53eb\u7b2c\u4e94\u5171\u548c\u56fd", "part": "zhidao_train"}
{"question_type": "DESCRIPTION", "fact_or_opinion": "FACT", "id": 297, "question": "\u817e\u8baf\u89c6\u9891\u5f39\u5e55\u4e3a\u4ec0\u4e48\u6ca1\u4e86", "part": "zhidao_train"}
{"question_type": "DESCRIPTION", "fact_or_opinion": "FACT", "id": 70950, "question": "\u8c37\u7ef4\u7d20\u7ef4\u751f\u7d20b1\u7684\u529f\u6548", "part": "zhidao_train"}
{"question_type": "DESCRIPTION", "fact_or_opinion": "OPINION", "id": 72250, "question": "\u53e4\u4ee3\u6253\u677f\u5b50\u6709\u591a\u75bc", "part": "zhidao_train"}
{"question_type": "ENTITY", "fact_or_opinion": "OPINION", "id": 6118, "question": "\u98ce\u6295\u516c\u53f8\u6392\u540d", "part": "zhidao_train"}
{"question_type": "DESCRIPTION", "fact_or_opinion": "OPINION", "id": 48607, "question": "\u65b0\u624b\u4f1a\u8ba1\u6ca1\u4eba\u5e26\u600e\u4e48\u529e", "part": "zhidao_train"}
{"question_type": "DESCRIPTION", "fact_or_opinion": "FACT", "id": 9854, "question": "\u5fae\u4fe1\u516c\u4f17\u53f7\u7c7b\u578b\u533a\u522b", "part": "zhidao_train"}
{"question_type": "YES_NO", "fact_or_opinion": "OPINION", "id": 7233, "question": "\u9ec4\u91d1\u94b1\u5305\u6295\u8d44\u53ef\u9760\u5417", "part": "zhidao_train"}
{"question_type": "ENTITY", "fact_or_opinion": "OPINION", "id": 30325, "question": "\u540c\u623f\u51e0\u5929\u53ef\u4ee5\u6d4b\u51fa\u6765", "part": "zhidao_train"}
{"question_type": "DESCRIPTION", "fact_or_opinion": "OPINION", "id": 86257, "question": "\u9e21\u8089\u7ca5\u7684\u505a\u6cd5", "part": "zhidao_train"}
{"question_type": "YES_NO", "fact_or_opinion": "FACT", "id": 64837, "question": "\u6237\u53e3\u548c\u6863\u6848\u4e0d\u5728\u540c\u4e00\u4e2a\u5730\u65b9\u53ef\u4ee5\u5417", "part": "zhidao_train"}
{"question_type": "YES_NO", "fact_or_opinion": "FACT", "id": 23343, "question": "\u4e94\u4e00\u9ad8\u901f\u516c\u8def\u514d\u8d39\u5417", "part": "zhidao_train"}
{"question_type": "YES_NO", "fact_or_opinion": "OPINION", "id": 8179, "question": "\u957f\u6c99\u9650\u8d2d\u5417", "part": "zhidao_train"}
{"question_type": "DESCRIPTION", "fact_or_opinion": "FACT", "id": 55518, "question": "cad\u79fb\u52a8\u53d8\u6210\u590d\u5236", "part": "zhidao_train"}
{"question_type": "YES_NO", "fact_or_opinion": "OPINION", "id": 68662, "question": "\u94a2\u5316\u819c\u84dd\u5149\u548c\u666e\u901a\u6709\u533a\u522b\u5417", "part": "zhidao_train"}
{"question_type": "DESCRIPTION", "fact_or_opinion": "FACT", "id": 63614, "question": "\u5929\u5200\u5927\u8f7b\u529f\u600e\u4e48\u83b7\u5f97", "part": "zhidao_train"}
{"question_type": "DESCRIPTION", "fact_or_opinion": "OPINION", "id": 52791, "question": "\u6566\u539a\u8fd1\u4e49\u8bcd", "part": "zhidao_train"}
{"question_type": "ENTITY", "fact_or_opinion": "FACT", "id": 47102, "question": "dnf\u66b4\u8d70\u662f\u591a\u5c11\u7ea7\u6280\u80fd", "part": "zhidao_train"}
{"question_type": "DESCRIPTION", "fact_or_opinion": "FACT", "id": 29355, "question": "\u793e\u79d1\u7c7b\u8bba\u6587\u683c\u5f0f", "part": "zhidao_train"}
{"question_type": "ENTITY", "fact_or_opinion": "OPINION", "id": 59285, "question": "\u6797\u4fca\u6770\u5728\u534e\u7eb3\u4ec0\u4e48\u5730\u4f4d", "part": "zhidao_train"}
{"question_type": "ENTITY", "fact_or_opinion": "OPINION", "id": 43944, "question": "\u6c88\u9633\u79df\u8f66\u516c\u53f8\u54ea\u5bb6\u597d", "part": "zhidao_train"}
{"question_type": "ENTITY", "fact_or_opinion": "OPINION", "id": 70288, "question": "\u672b\u65e5\u65f6\u5728\u505a\u4ec0\u4e48\u88ab\u62ef\u6551", "part": "zhidao_train"}
{"question_type": "YES_NO", "fact_or_opinion": "OPINION", "id": 64012, "question": "\u679c\u6ce5\u5c5e\u4e8e\u6db2\u4f53\u5417", "part": "zhidao_train"}
{"question_type": "ENTITY", "fact_or_opinion": "FACT", "id": 17105, "question": "\u6ed1\u819c\u708e\u7684\u75c7\u72b6", "part": "zhidao_train"}